tml/__init__.py
tml/context.py
tml/markup.py
tml/parser.py
tml/tags.py
python_tml-1.0.2.dist-info/LICENSE
python_tml-1.0.2.dist-info/METADATA
python_tml-1.0.2.dist-info/WHEEL
python_tml-1.0.2.dist-info/top_level.txt
python_tml-1.0.2.dist-info/RECORD
