Metadata-Version: 2.1
Name: python-tml
Version: 1.0.2
Summary: A terminal markup language, inspired by tml
Home-page: https://github.com/jonghwanhyeon/python-tml
Author: Jonghwan Hyeon
Author-email: jonghwanhyeon93@gmail.com
License: MIT
Keywords: terminal,markup,languages
Classifier: Development Status :: 4 - Beta
Classifier: Intended Audience :: Developers
Classifier: License :: OSI Approved :: MIT License
Classifier: Programming Language :: Python :: 3
Classifier: Programming Language :: Python :: 3 :: Only
Requires-Python: >=3.7
License-File: LICENSE
Provides-Extra: dev
Requires-Dist: mypy ; extra == 'dev'
Requires-Dist: ruff ; extra == 'dev'
